source_auth0/__init__.py
source_auth0/manifest.yaml
source_auth0/run.py
source_auth0/schemas/clients.json
source_auth0/schemas/organization_member_roles.json
source_auth0/schemas/organization_members.json
source_auth0/schemas/organizations.json
source_auth0/schemas/users.json
source_auth0/source.py
source_auth0/spec.yaml
airbyte_source_auth0-0.5.16.dist-info/METADATA
airbyte_source_auth0-0.5.16.dist-info/WHEEL
airbyte_source_auth0-0.5.16.dist-info/entry_points.txt
airbyte_source_auth0-0.5.16.dist-info/RECORD
